odoo9_addon_openeducat_classroom-9.0.2.4.0-py2.7-nspkg.pth
odoo_addons/openeducat_classroom/__openerp__.py
odoo_addons/openeducat_classroom/classroom_menu.xml
odoo_addons/openeducat_classroom/__init__.py
odoo_addons/openeducat_classroom/security/ir.model.access.csv
odoo_addons/openeducat_classroom/models/classroom.py
odoo_addons/openeducat_classroom/models/__init__.py
odoo_addons/openeducat_classroom/models/facility_line.py
odoo_addons/openeducat_classroom/models/asset.py
odoo_addons/openeducat_classroom/i18n/openeducat_classroom.pot
odoo_addons/openeducat_classroom/views/classroom_view.xml
odoo_addons/openeducat_classroom/demo/op.facility.line.csv
odoo_addons/openeducat_classroom/demo/op.classroom.csv
odoo_addons/openeducat_classroom/static/description/openeducat_logo.png
odoo_addons/openeducat_classroom/static/description/classroom.png
odoo_addons/openeducat_classroom/static/description/openeducat_classroom_banner.jpg
odoo_addons/openeducat_classroom/static/description/index.html
odoo_addons/openeducat_classroom/static/description/icon.png
odoo9_addon_openeducat_classroom-9.0.2.4.0.dist-info/top_level.txt
odoo9_addon_openeducat_classroom-9.0.2.4.0.dist-info/WHEEL
odoo9_addon_openeducat_classroom-9.0.2.4.0.dist-info/RECORD
odoo9_addon_openeducat_classroom-9.0.2.4.0.dist-info/metadata.json
odoo9_addon_openeducat_classroom-9.0.2.4.0.dist-info/DESCRIPTION.rst
odoo9_addon_openeducat_classroom-9.0.2.4.0.dist-info/METADATA
odoo9_addon_openeducat_classroom-9.0.2.4.0.dist-info/namespace_packages.txt
